{"is_source_file": false, "format": "", "description": "", "external_files": [], "external_methods": [], "published": [], "classes": [], "methods": [], "calls": [], "search-terms": [], "state": 2, "file_id": 3, "knowledge_revision": 40, "git_revision": "c5f75cccaae87debdd0b78df05e169c33235dd56", "hash": "1cb85c6a9c30034ec21aaceeea666d8e", "format-version": 4, "code-base-name": "recipe_frontend", "filename": "recipe_frontend/app.json", "revision_history": [{"40": "c5f75cccaae87debdd0b78df05e169c33235dd56"}]}